{
  "version": "6.0",
  "nxVersion": "19.6.2",
  "deps": {
    "autospace": "file:",
    "husky": "^8.0.0",
    "nx": "19.6.2",
    "prettier": "^3.0.0",
    "typescript": "^5.5.4"
  },
  "pathMappings": {},
  "nxJsonPlugins": [],
  "fileMap": {
    "nonProjectFiles": [
      {
        "file": "tsconfig.json",
        "hash": "17553373538878946914"
      },
      {
        "file": ".gitignore",
        "hash": "8258668164414709802"
      },
      {
        "file": "yarn.lock",
        "hash": "2061531463656504586"
      },
      {
        "file": "package.json",
        "hash": "13780783282132288"
      },
      {
        "file": "nx.json",
        "hash": "10654315332906694547"
      },
      {
        "file": ".prettierrc",
        "hash": "15185374989492744169"
      },
      {
        "file": ".husky/pre-commit",
        "hash": "3309188075304346290"
      },
      {
        "file": "README.md",
        "hash": "9383568174200241605"
      },
      {
        "file": "package-lock.json",
        "hash": "7652867624783744996"
      }
    ],
    "projectFileMap": {
      "@autospace/forms": [
        {
          "file": "libs/forms/package-lock.json",
          "hash": "14837118094832395118"
        },
        {
          "file": "libs/forms/package.json",
          "hash": "6253168937831664220",
          "deps": [
            "npm:@hookform/resolvers",
            "npm:react-hook-form",
            "npm:zod"
          ]
        },
        {
          "file": "libs/forms/src/login.tsx",
          "hash": "1014189757167921858"
        },
        {
          "file": "libs/forms/src/register.tsx",
          "hash": "13399419665511730166"
        },
        {
          "file": "libs/forms/src/schemas.ts",
          "hash": "16014452263787135725"
        },
        {
          "file": "libs/forms/src/searchGarages.tsx",
          "hash": "15591399080711938975"
        },
        {
          "file": "libs/forms/tsconfig.json",
          "hash": "12053352178282715962"
        },
        {
          "file": "libs/forms/src/adapters/searchFormAdapter.ts",
          "hash": "1344782089110698052"
        },
        {
          "file": "libs/forms/src/adapters/util.ts",
          "hash": "13651936096134941573"
        }
      ],
      "@autospace/network": [
        {
          "file": "libs/network/codegen.ts",
          "hash": "596092472759370737"
        },
        {
          "file": "libs/network/next-auth.d.ts",
          "hash": "6929401787329986376"
        },
        {
          "file": "libs/network/package-lock.json",
          "hash": "11894992049883542789"
        },
        {
          "file": "libs/network/package.json",
          "hash": "16413782871599866796",
          "deps": [
            "npm:react",
            "npm:@graphql-codegen/cli",
            "npm:@graphql-codegen/named-operations-object",
            "npm:@graphql-codegen/typed-document-node",
            "npm:@parcel/watcher",
            "npm:@types/jsonwebtoken",
            "npm:@apollo/client",
            "npm:jsonwebtoken"
          ]
        },
        {
          "file": "libs/network/src/config/apollo.tsx",
          "hash": "18065035441060385382"
        },
        {
          "file": "libs/network/src/config/authOptions.ts",
          "hash": "9744023034218744097"
        },
        {
          "file": "libs/network/src/fetch/index.ts",
          "hash": "2908994720606023079"
        },
        {
          "file": "libs/network/src/gql/generated.tsx",
          "hash": "7179609746584705517"
        },
        {
          "file": "libs/network/src/gql/queries.graphql",
          "hash": "1871425878431069797"
        },
        {
          "file": "libs/network/tsconfig.json",
          "hash": "12053352178282715962"
        }
      ],
      "@autospace/api": [
        {
          "file": "apps/api/.env.example",
          "hash": "1887901518666600425"
        },
        {
          "file": "apps/api/.eslintrc.js",
          "hash": "7461846271827386206"
        },
        {
          "file": "apps/api/.gitignore",
          "hash": "547753584460066287"
        },
        {
          "file": "apps/api/.prettierrc",
          "hash": "5008776440579340246"
        },
        {
          "file": "apps/api/README.md",
          "hash": "3076710801678341246"
        },
        {
          "file": "apps/api/docker-compose.yml",
          "hash": "13679263941518240661"
        },
        {
          "file": "apps/api/nest-cli.json",
          "hash": "7303373952232276918"
        },
        {
          "file": "apps/api/package.json",
          "hash": "5205087221004780950",
          "deps": [
            "npm:@nestjs/cli@10.4.5",
            "npm:@nestjs/schematics@10.1.4",
            "npm:@nestjs/testing@10.4.1",
            "npm:@types/express",
            "npm:@types/jest",
            "npm:@types/node",
            "npm:@types/supertest",
            "npm:@typescript-eslint/eslint-plugin",
            "npm:@typescript-eslint/parser@7.18.0",
            "npm:eslint",
            "npm:eslint-config-prettier",
            "npm:eslint-plugin-prettier",
            "npm:jest",
            "npm:nestjs-prisma-codegen",
            "npm:prettier",
            "npm:prisma",
            "npm:source-map-support",
            "npm:supertest",
            "npm:ts-jest",
            "npm:ts-loader",
            "npm:ts-node",
            "npm:tsconfig-paths",
            "npm:typescript",
            "npm:@apollo/server",
            "@autospace/sample-lib",
            "@autospace/network",
            "npm:@nestjs/apollo@12.2.0",
            "npm:@nestjs/common@10.4.1",
            "npm:@nestjs/config@3.2.3",
            "npm:@nestjs/core@10.4.1",
            "npm:@nestjs/graphql@12.2.0",
            "npm:@nestjs/jwt@10.2.0",
            "npm:@nestjs/platform-express@10.4.1",
            "npm:@nestjs/swagger@7.4.0",
            "npm:@prisma/client",
            "npm:bcryptjs",
            "npm:class-transformer",
            "npm:class-validator",
            "npm:graphql",
            "npm:reflect-metadata",
            "npm:rxjs",
            "npm:uuid"
          ]
        },
        {
          "file": "apps/api/prisma/migrations/20240819161658_init/migration.sql",
          "hash": "17991940606836201096"
        },
        {
          "file": "apps/api/prisma/migrations/20240823173453_add_user_image/migration.sql",
          "hash": "2492629257202547793"
        },
        {
          "file": "apps/api/prisma/migrations/20240824075444_init/migration.sql",
          "hash": "3727955513567689201"
        },
        {
          "file": "apps/api/prisma/migrations/migration_lock.toml",
          "hash": "5278839983338653787"
        },
        {
          "file": "apps/api/prisma/schema.prisma",
          "hash": "4423606940400409847"
        },
        {
          "file": "apps/api/src/app.controller.spec.ts",
          "hash": "2727664763654384995"
        },
        {
          "file": "apps/api/src/app.controller.ts",
          "hash": "4552329938751326480"
        },
        {
          "file": "apps/api/src/app.module.ts",
          "hash": "10314010848017747588"
        },
        {
          "file": "apps/api/src/app.service.ts",
          "hash": "13790631590534670665"
        },
        {
          "file": "apps/api/src/common/auth/auth.decorator.ts",
          "hash": "12751477917174492460"
        },
        {
          "file": "apps/api/src/common/auth/auth.guard.ts",
          "hash": "17702836144080331271"
        },
        {
          "file": "apps/api/src/common/auth/util.ts",
          "hash": "11321517643038472839"
        },
        {
          "file": "apps/api/src/common/dtos/common.dto.ts",
          "hash": "1934167735380686350"
        },
        {
          "file": "apps/api/src/common/dtos/common.input.ts",
          "hash": "2977824803178952216"
        },
        {
          "file": "apps/api/src/common/prisma/prisma.module.ts",
          "hash": "10238961258611182846"
        },
        {
          "file": "apps/api/src/common/prisma/prisma.service.ts",
          "hash": "1045870061148676476"
        },
        {
          "file": "apps/api/src/common/types/index.ts",
          "hash": "12784110671031659993"
        },
        {
          "file": "apps/api/src/main.ts",
          "hash": "1586354829395608676"
        },
        {
          "file": "apps/api/src/models/addresses/addresses.module.ts",
          "hash": "15374675243169162368"
        },
        {
          "file": "apps/api/src/models/addresses/graphql/addresses.resolver.ts",
          "hash": "6644123331857915489"
        },
        {
          "file": "apps/api/src/models/addresses/graphql/addresses.service.ts",
          "hash": "17443493595934784320"
        },
        {
          "file": "apps/api/src/models/addresses/graphql/dtos/create-address.input.ts",
          "hash": "8195320084703773256"
        },
        {
          "file": "apps/api/src/models/addresses/graphql/dtos/find.args.ts",
          "hash": "1675086944397286169"
        },
        {
          "file": "apps/api/src/models/addresses/graphql/dtos/order-by.args.ts",
          "hash": "8027549726527316744"
        },
        {
          "file": "apps/api/src/models/addresses/graphql/dtos/update-address.input.ts",
          "hash": "8138159637577382246"
        },
        {
          "file": "apps/api/src/models/addresses/graphql/dtos/where.args.ts",
          "hash": "5562385794362152483"
        },
        {
          "file": "apps/api/src/models/addresses/graphql/entity/address.entity.ts",
          "hash": "9538083737040504333"
        },
        {
          "file": "apps/api/src/models/addresses/rest/addresses.controller.ts",
          "hash": "4582011941624847838"
        },
        {
          "file": "apps/api/src/models/addresses/rest/dtos/create.dto.ts",
          "hash": "5973497228726931901"
        },
        {
          "file": "apps/api/src/models/addresses/rest/dtos/query.dto.ts",
          "hash": "5615377448071536151"
        },
        {
          "file": "apps/api/src/models/addresses/rest/dtos/update.dto.ts",
          "hash": "2108188635898133991"
        },
        {
          "file": "apps/api/src/models/addresses/rest/entity/address.entity.ts",
          "hash": "7434152563245437601"
        },
        {
          "file": "apps/api/src/models/admins/admins.module.ts",
          "hash": "4738461424662311593"
        },
        {
          "file": "apps/api/src/models/admins/graphql/admins.resolver.ts",
          "hash": "11325717581154843085"
        },
        {
          "file": "apps/api/src/models/admins/graphql/admins.service.ts",
          "hash": "13023024572136706797"
        },
        {
          "file": "apps/api/src/models/admins/graphql/dtos/create-admin.input.ts",
          "hash": "4274518748932013740"
        },
        {
          "file": "apps/api/src/models/admins/graphql/dtos/find.args.ts",
          "hash": "13408183666605023750"
        },
        {
          "file": "apps/api/src/models/admins/graphql/dtos/order-by.args.ts",
          "hash": "1143295781196607492"
        },
        {
          "file": "apps/api/src/models/admins/graphql/dtos/update-admin.input.ts",
          "hash": "4893257919011187807"
        },
        {
          "file": "apps/api/src/models/admins/graphql/dtos/where.args.ts",
          "hash": "15424389750149324140"
        },
        {
          "file": "apps/api/src/models/admins/graphql/entity/admin.entity.ts",
          "hash": "3593735390156868611"
        },
        {
          "file": "apps/api/src/models/admins/rest/admins.controller.ts",
          "hash": "17610268504226358458"
        },
        {
          "file": "apps/api/src/models/admins/rest/dtos/create.dto.ts",
          "hash": "15523898372017336151"
        },
        {
          "file": "apps/api/src/models/admins/rest/dtos/query.dto.ts",
          "hash": "7080211725021192840"
        },
        {
          "file": "apps/api/src/models/admins/rest/dtos/update.dto.ts",
          "hash": "9145812469421036285"
        },
        {
          "file": "apps/api/src/models/admins/rest/entity/admin.entity.ts",
          "hash": "2824641295148983660"
        },
        {
          "file": "apps/api/src/models/booking-timelines/booking-timelines.module.ts",
          "hash": "1272923478561682570"
        },
        {
          "file": "apps/api/src/models/booking-timelines/graphql/booking-timelines.resolver.ts",
          "hash": "2264500161768603470"
        },
        {
          "file": "apps/api/src/models/booking-timelines/graphql/booking-timelines.service.ts",
          "hash": "1983140856002865548"
        },
        {
          "file": "apps/api/src/models/booking-timelines/graphql/dtos/create-booking-timeline.input.ts",
          "hash": "12141820366142736630"
        },
        {
          "file": "apps/api/src/models/booking-timelines/graphql/dtos/find.args.ts",
          "hash": "5356553165672501193"
        },
        {
          "file": "apps/api/src/models/booking-timelines/graphql/dtos/order-by.args.ts",
          "hash": "2087326374233380156"
        },
        {
          "file": "apps/api/src/models/booking-timelines/graphql/dtos/update-booking-timeline.input.ts",
          "hash": "5832282326470138751"
        },
        {
          "file": "apps/api/src/models/booking-timelines/graphql/dtos/where.args.ts",
          "hash": "18216016323439012804"
        },
        {
          "file": "apps/api/src/models/booking-timelines/graphql/entity/booking-timeline.entity.ts",
          "hash": "8056448873318086145"
        },
        {
          "file": "apps/api/src/models/booking-timelines/rest/booking-timelines.controller.ts",
          "hash": "8010650077399855735"
        },
        {
          "file": "apps/api/src/models/booking-timelines/rest/dtos/create.dto.ts",
          "hash": "10186244929522834072"
        },
        {
          "file": "apps/api/src/models/booking-timelines/rest/dtos/query.dto.ts",
          "hash": "10180705468096064848"
        },
        {
          "file": "apps/api/src/models/booking-timelines/rest/dtos/update.dto.ts",
          "hash": "15390842431168200978"
        },
        {
          "file": "apps/api/src/models/booking-timelines/rest/entity/booking-timeline.entity.ts",
          "hash": "3084799871593329544"
        },
        {
          "file": "apps/api/src/models/bookings/bookings.module.ts",
          "hash": "16865496499574462624"
        },
        {
          "file": "apps/api/src/models/bookings/graphql/bookings.resolver.ts",
          "hash": "16824518944987020670"
        },
        {
          "file": "apps/api/src/models/bookings/graphql/bookings.service.ts",
          "hash": "1763767741506501651"
        },
        {
          "file": "apps/api/src/models/bookings/graphql/dtos/create-booking.input.ts",
          "hash": "12644221062510548519"
        },
        {
          "file": "apps/api/src/models/bookings/graphql/dtos/find.args.ts",
          "hash": "1526111400225758213"
        },
        {
          "file": "apps/api/src/models/bookings/graphql/dtos/order-by.args.ts",
          "hash": "16976398914263542579"
        },
        {
          "file": "apps/api/src/models/bookings/graphql/dtos/update-booking.input.ts",
          "hash": "6902512710910894669"
        },
        {
          "file": "apps/api/src/models/bookings/graphql/dtos/where.args.ts",
          "hash": "9853885310310182590"
        },
        {
          "file": "apps/api/src/models/bookings/graphql/entity/booking.entity.ts",
          "hash": "13032902953279133568"
        },
        {
          "file": "apps/api/src/models/bookings/rest/bookings.controller.ts",
          "hash": "8974997791478190338"
        },
        {
          "file": "apps/api/src/models/bookings/rest/dtos/create.dto.ts",
          "hash": "9917367566063690546"
        },
        {
          "file": "apps/api/src/models/bookings/rest/dtos/query.dto.ts",
          "hash": "6830776203287769239"
        },
        {
          "file": "apps/api/src/models/bookings/rest/dtos/update.dto.ts",
          "hash": "7035046986723546289"
        },
        {
          "file": "apps/api/src/models/bookings/rest/entity/booking.entity.ts",
          "hash": "1082000352771629791"
        },
        {
          "file": "apps/api/src/models/companies/companies.module.ts",
          "hash": "4306063558940206094"
        },
        {
          "file": "apps/api/src/models/companies/graphql/companies.resolver.ts",
          "hash": "5081208787798694594"
        },
        {
          "file": "apps/api/src/models/companies/graphql/companies.service.ts",
          "hash": "10992815672465537772"
        },
        {
          "file": "apps/api/src/models/companies/graphql/dtos/create-company.input.ts",
          "hash": "4256794090230956439"
        },
        {
          "file": "apps/api/src/models/companies/graphql/dtos/find.args.ts",
          "hash": "5308853125863754444"
        },
        {
          "file": "apps/api/src/models/companies/graphql/dtos/order-by.args.ts",
          "hash": "10431428341591324642"
        },
        {
          "file": "apps/api/src/models/companies/graphql/dtos/update-company.input.ts",
          "hash": "6076802622885185298"
        },
        {
          "file": "apps/api/src/models/companies/graphql/dtos/where.args.ts",
          "hash": "13999033314946946941"
        },
        {
          "file": "apps/api/src/models/companies/graphql/entity/company.entity.ts",
          "hash": "8859173058575983972"
        },
        {
          "file": "apps/api/src/models/companies/rest/companies.controller.ts",
          "hash": "6181195385193717714"
        },
        {
          "file": "apps/api/src/models/companies/rest/dtos/create.dto.ts",
          "hash": "17136206346823413708"
        },
        {
          "file": "apps/api/src/models/companies/rest/dtos/query.dto.ts",
          "hash": "16639942452150029069"
        },
        {
          "file": "apps/api/src/models/companies/rest/dtos/update.dto.ts",
          "hash": "4770577409362078266"
        },
        {
          "file": "apps/api/src/models/companies/rest/entity/company.entity.ts",
          "hash": "798513466655720186"
        },
        {
          "file": "apps/api/src/models/customers/customers.module.ts",
          "hash": "2125091023888562516"
        },
        {
          "file": "apps/api/src/models/customers/graphql/customers.resolver.ts",
          "hash": "11453722148001750698"
        },
        {
          "file": "apps/api/src/models/customers/graphql/customers.service.ts",
          "hash": "2524000950476720577"
        },
        {
          "file": "apps/api/src/models/customers/graphql/dtos/create-customer.input.ts",
          "hash": "8902072384852894635"
        },
        {
          "file": "apps/api/src/models/customers/graphql/dtos/find.args.ts",
          "hash": "10089267568989802416"
        },
        {
          "file": "apps/api/src/models/customers/graphql/dtos/order-by.args.ts",
          "hash": "16040572943251504426"
        },
        {
          "file": "apps/api/src/models/customers/graphql/dtos/update-customer.input.ts",
          "hash": "13507374201404190390"
        },
        {
          "file": "apps/api/src/models/customers/graphql/dtos/where.args.ts",
          "hash": "18378186425366940592"
        },
        {
          "file": "apps/api/src/models/customers/graphql/entity/customer.entity.ts",
          "hash": "3002676693001465161"
        },
        {
          "file": "apps/api/src/models/customers/rest/customers.controller.ts",
          "hash": "9260244904109096041"
        },
        {
          "file": "apps/api/src/models/customers/rest/dtos/create.dto.ts",
          "hash": "4810700751728303072"
        },
        {
          "file": "apps/api/src/models/customers/rest/dtos/query.dto.ts",
          "hash": "141776639450986552"
        },
        {
          "file": "apps/api/src/models/customers/rest/dtos/update.dto.ts",
          "hash": "543654478586746015"
        },
        {
          "file": "apps/api/src/models/customers/rest/entity/customer.entity.ts",
          "hash": "15737395502665210062"
        },
        {
          "file": "apps/api/src/models/garages/garages.module.ts",
          "hash": "10592709878496067202"
        },
        {
          "file": "apps/api/src/models/garages/graphql/dtos/create-garage.input.ts",
          "hash": "6987542002460689093"
        },
        {
          "file": "apps/api/src/models/garages/graphql/dtos/find.args.ts",
          "hash": "6325705087882666514"
        },
        {
          "file": "apps/api/src/models/garages/graphql/dtos/order-by.args.ts",
          "hash": "6769604890093497765"
        },
        {
          "file": "apps/api/src/models/garages/graphql/dtos/search-filter.input.ts",
          "hash": "13277975504210642639"
        },
        {
          "file": "apps/api/src/models/garages/graphql/dtos/update-garage.input.ts",
          "hash": "7546356706032945141"
        },
        {
          "file": "apps/api/src/models/garages/graphql/dtos/where.args.ts",
          "hash": "4786359886589183799"
        },
        {
          "file": "apps/api/src/models/garages/graphql/entity/garage.entity.ts",
          "hash": "642081303967656316"
        },
        {
          "file": "apps/api/src/models/garages/graphql/garages.resolver.ts",
          "hash": "14087631345974711223"
        },
        {
          "file": "apps/api/src/models/garages/graphql/garages.service.ts",
          "hash": "17373902231933921925"
        },
        {
          "file": "apps/api/src/models/garages/rest/dtos/create.dto.ts",
          "hash": "13305703168688261261"
        },
        {
          "file": "apps/api/src/models/garages/rest/dtos/query.dto.ts",
          "hash": "6520019553041140053"
        },
        {
          "file": "apps/api/src/models/garages/rest/dtos/update.dto.ts",
          "hash": "7663909214550437717"
        },
        {
          "file": "apps/api/src/models/garages/rest/entity/garage.entity.ts",
          "hash": "14315429045853950813"
        },
        {
          "file": "apps/api/src/models/garages/rest/garages.controller.ts",
          "hash": "13613106251337460389"
        },
        {
          "file": "apps/api/src/models/managers/graphql/dtos/create-manager.input.ts",
          "hash": "5998003354651366838"
        },
        {
          "file": "apps/api/src/models/managers/graphql/dtos/find.args.ts",
          "hash": "4280557329145666654"
        },
        {
          "file": "apps/api/src/models/managers/graphql/dtos/order-by.args.ts",
          "hash": "9413289684382078090"
        },
        {
          "file": "apps/api/src/models/managers/graphql/dtos/update-manager.input.ts",
          "hash": "8077124430204978563"
        },
        {
          "file": "apps/api/src/models/managers/graphql/dtos/where.args.ts",
          "hash": "5573157682545588483"
        },
        {
          "file": "apps/api/src/models/managers/graphql/entity/manager.entity.ts",
          "hash": "7881693251712000514"
        },
        {
          "file": "apps/api/src/models/managers/graphql/managers.resolver.ts",
          "hash": "15175908973156884393"
        },
        {
          "file": "apps/api/src/models/managers/graphql/managers.service.ts",
          "hash": "2378997029665601055"
        },
        {
          "file": "apps/api/src/models/managers/managers.module.ts",
          "hash": "10076187704399785676"
        },
        {
          "file": "apps/api/src/models/managers/rest/dtos/create.dto.ts",
          "hash": "4522823378848645806"
        },
        {
          "file": "apps/api/src/models/managers/rest/dtos/query.dto.ts",
          "hash": "2643775087285806195"
        },
        {
          "file": "apps/api/src/models/managers/rest/dtos/update.dto.ts",
          "hash": "1231153556571171228"
        },
        {
          "file": "apps/api/src/models/managers/rest/entity/manager.entity.ts",
          "hash": "14869666277840907104"
        },
        {
          "file": "apps/api/src/models/managers/rest/managers.controller.ts",
          "hash": "9465220124846261615"
        },
        {
          "file": "apps/api/src/models/reviews/graphql/dtos/create-review.input.ts",
          "hash": "4417758055438571468"
        },
        {
          "file": "apps/api/src/models/reviews/graphql/dtos/find.args.ts",
          "hash": "13984015861437398408"
        },
        {
          "file": "apps/api/src/models/reviews/graphql/dtos/order-by.args.ts",
          "hash": "16646557847529851841"
        },
        {
          "file": "apps/api/src/models/reviews/graphql/dtos/update-review.input.ts",
          "hash": "8638751309347606316"
        },
        {
          "file": "apps/api/src/models/reviews/graphql/dtos/where.args.ts",
          "hash": "16640698637975563480"
        },
        {
          "file": "apps/api/src/models/reviews/graphql/entity/review.entity.ts",
          "hash": "11216627132859964842"
        },
        {
          "file": "apps/api/src/models/reviews/graphql/reviews.resolver.ts",
          "hash": "12115117958717921394"
        },
        {
          "file": "apps/api/src/models/reviews/graphql/reviews.service.ts",
          "hash": "16352726812126658048"
        },
        {
          "file": "apps/api/src/models/reviews/rest/dtos/create.dto.ts",
          "hash": "8116580300878302506"
        },
        {
          "file": "apps/api/src/models/reviews/rest/dtos/query.dto.ts",
          "hash": "10418455327959866725"
        },
        {
          "file": "apps/api/src/models/reviews/rest/dtos/update.dto.ts",
          "hash": "9010874951854967880"
        },
        {
          "file": "apps/api/src/models/reviews/rest/entity/review.entity.ts",
          "hash": "10295992743393032"
        },
        {
          "file": "apps/api/src/models/reviews/rest/reviews.controller.ts",
          "hash": "7532771833366111909"
        },
        {
          "file": "apps/api/src/models/reviews/reviews.module.ts",
          "hash": "11161434567161017952"
        },
        {
          "file": "apps/api/src/models/slots/graphql/dtos/create-slot.input.ts",
          "hash": "14486734107106836961"
        },
        {
          "file": "apps/api/src/models/slots/graphql/dtos/find.args.ts",
          "hash": "4369939551746444222"
        },
        {
          "file": "apps/api/src/models/slots/graphql/dtos/order-by.args.ts",
          "hash": "11077375871622866299"
        },
        {
          "file": "apps/api/src/models/slots/graphql/dtos/update-slot.input.ts",
          "hash": "9158092624927202459"
        },
        {
          "file": "apps/api/src/models/slots/graphql/dtos/where.args.ts",
          "hash": "4260584533937827296"
        },
        {
          "file": "apps/api/src/models/slots/graphql/entity/slot.entity.ts",
          "hash": "3627293822976448165"
        },
        {
          "file": "apps/api/src/models/slots/graphql/slots.resolver.ts",
          "hash": "2920931479094413727"
        },
        {
          "file": "apps/api/src/models/slots/graphql/slots.service.ts",
          "hash": "17683765459799078902"
        },
        {
          "file": "apps/api/src/models/slots/rest/dtos/create.dto.ts",
          "hash": "15359943893231034656"
        },
        {
          "file": "apps/api/src/models/slots/rest/dtos/query.dto.ts",
          "hash": "8257339456892598976"
        },
        {
          "file": "apps/api/src/models/slots/rest/dtos/update.dto.ts",
          "hash": "10779470290763309055"
        },
        {
          "file": "apps/api/src/models/slots/rest/entity/slot.entity.ts",
          "hash": "7934285414194445397"
        },
        {
          "file": "apps/api/src/models/slots/rest/slots.controller.ts",
          "hash": "18317451583292391778"
        },
        {
          "file": "apps/api/src/models/slots/slots.module.ts",
          "hash": "5364568585723142391"
        },
        {
          "file": "apps/api/src/models/users/graphql/dtos/create-user.input.ts",
          "hash": "5389820201915775305"
        },
        {
          "file": "apps/api/src/models/users/graphql/dtos/find.args.ts",
          "hash": "3230308515392106176"
        },
        {
          "file": "apps/api/src/models/users/graphql/dtos/order-by.args.ts",
          "hash": "16427631934841114141"
        },
        {
          "file": "apps/api/src/models/users/graphql/dtos/update-user.input.ts",
          "hash": "12457025114288375511"
        },
        {
          "file": "apps/api/src/models/users/graphql/dtos/where.args.ts",
          "hash": "12234893871334376684"
        },
        {
          "file": "apps/api/src/models/users/graphql/entity/user.entity.ts",
          "hash": "6016928478860133471"
        },
        {
          "file": "apps/api/src/models/users/graphql/users.resolver.ts",
          "hash": "6232240427522716683"
        },
        {
          "file": "apps/api/src/models/users/graphql/users.service.ts",
          "hash": "8620176869073858195"
        },
        {
          "file": "apps/api/src/models/users/rest/dtos/create.dto.ts",
          "hash": "3904513872696789038"
        },
        {
          "file": "apps/api/src/models/users/rest/dtos/query.dto.ts",
          "hash": "8482205000946766216"
        },
        {
          "file": "apps/api/src/models/users/rest/dtos/update.dto.ts",
          "hash": "12881685194223706454"
        },
        {
          "file": "apps/api/src/models/users/rest/entity/user.entity.ts",
          "hash": "15729492598828657666"
        },
        {
          "file": "apps/api/src/models/users/rest/users.controller.ts",
          "hash": "11185857105791276802"
        },
        {
          "file": "apps/api/src/models/users/users.module.ts",
          "hash": "15163604134336005369"
        },
        {
          "file": "apps/api/src/models/valet-assignments/graphql/dtos/create-valet-assignment.input.ts",
          "hash": "272818453898137138"
        },
        {
          "file": "apps/api/src/models/valet-assignments/graphql/dtos/find.args.ts",
          "hash": "11184611214877231935"
        },
        {
          "file": "apps/api/src/models/valet-assignments/graphql/dtos/order-by.args.ts",
          "hash": "3828989050154924509"
        },
        {
          "file": "apps/api/src/models/valet-assignments/graphql/dtos/update-valet-assignment.input.ts",
          "hash": "17818925688700540908"
        },
        {
          "file": "apps/api/src/models/valet-assignments/graphql/dtos/where.args.ts",
          "hash": "13388632136813893782"
        },
        {
          "file": "apps/api/src/models/valet-assignments/graphql/entity/valet-assignment.entity.ts",
          "hash": "10329744609825243007"
        },
        {
          "file": "apps/api/src/models/valet-assignments/graphql/valet-assignments.resolver.ts",
          "hash": "16045048924426081201"
        },
        {
          "file": "apps/api/src/models/valet-assignments/graphql/valet-assignments.service.ts",
          "hash": "1403106214946814425"
        },
        {
          "file": "apps/api/src/models/valet-assignments/rest/dtos/create.dto.ts",
          "hash": "3655116953044976143"
        },
        {
          "file": "apps/api/src/models/valet-assignments/rest/dtos/query.dto.ts",
          "hash": "8001883317906684684"
        },
        {
          "file": "apps/api/src/models/valet-assignments/rest/dtos/update.dto.ts",
          "hash": "16635322008335025148"
        },
        {
          "file": "apps/api/src/models/valet-assignments/rest/entity/valet-assignment.entity.ts",
          "hash": "15179389903993119797"
        },
        {
          "file": "apps/api/src/models/valet-assignments/rest/valet-assignments.controller.ts",
          "hash": "134114468891857203"
        },
        {
          "file": "apps/api/src/models/valet-assignments/valet-assignments.module.ts",
          "hash": "18255735802999632911"
        },
        {
          "file": "apps/api/src/models/valets/graphql/dtos/create-valet.input.ts",
          "hash": "12898008315642816808"
        },
        {
          "file": "apps/api/src/models/valets/graphql/dtos/find.args.ts",
          "hash": "7000181736894721833"
        },
        {
          "file": "apps/api/src/models/valets/graphql/dtos/order-by.args.ts",
          "hash": "12755485187771452230"
        },
        {
          "file": "apps/api/src/models/valets/graphql/dtos/update-valet.input.ts",
          "hash": "9216091028215487592"
        },
        {
          "file": "apps/api/src/models/valets/graphql/dtos/where.args.ts",
          "hash": "1167353193908996036"
        },
        {
          "file": "apps/api/src/models/valets/graphql/entity/valet.entity.ts",
          "hash": "7597761955002931321"
        },
        {
          "file": "apps/api/src/models/valets/graphql/valets.resolver.ts",
          "hash": "6497970380919007872"
        },
        {
          "file": "apps/api/src/models/valets/graphql/valets.service.ts",
          "hash": "13405651455243706499"
        },
        {
          "file": "apps/api/src/models/valets/rest/dtos/create.dto.ts",
          "hash": "2418046962159871488"
        },
        {
          "file": "apps/api/src/models/valets/rest/dtos/query.dto.ts",
          "hash": "16080614293463294513"
        },
        {
          "file": "apps/api/src/models/valets/rest/dtos/update.dto.ts",
          "hash": "14439731368329426994"
        },
        {
          "file": "apps/api/src/models/valets/rest/entity/valet.entity.ts",
          "hash": "3979843185224638112"
        },
        {
          "file": "apps/api/src/models/valets/rest/valets.controller.ts",
          "hash": "9162453186548591393"
        },
        {
          "file": "apps/api/src/models/valets/valets.module.ts",
          "hash": "6544572483498687927"
        },
        {
          "file": "apps/api/src/models/verifications/graphql/dtos/create-verification.input.ts",
          "hash": "8564371668120005566"
        },
        {
          "file": "apps/api/src/models/verifications/graphql/dtos/find.args.ts",
          "hash": "13062156308073452762"
        },
        {
          "file": "apps/api/src/models/verifications/graphql/dtos/order-by.args.ts",
          "hash": "4203451613838262221"
        },
        {
          "file": "apps/api/src/models/verifications/graphql/dtos/update-verification.input.ts",
          "hash": "15070848830887510708"
        },
        {
          "file": "apps/api/src/models/verifications/graphql/dtos/where.args.ts",
          "hash": "8858341347350207596"
        },
        {
          "file": "apps/api/src/models/verifications/graphql/entity/verification.entity.ts",
          "hash": "388179819289658091"
        },
        {
          "file": "apps/api/src/models/verifications/graphql/verifications.resolver.ts",
          "hash": "12781919226519126474"
        },
        {
          "file": "apps/api/src/models/verifications/graphql/verifications.service.ts",
          "hash": "7551690212312552662"
        },
        {
          "file": "apps/api/src/models/verifications/rest/dtos/create.dto.ts",
          "hash": "16324272126504573287"
        },
        {
          "file": "apps/api/src/models/verifications/rest/dtos/query.dto.ts",
          "hash": "6483307270594122667"
        },
        {
          "file": "apps/api/src/models/verifications/rest/dtos/update.dto.ts",
          "hash": "15938415042086471038"
        },
        {
          "file": "apps/api/src/models/verifications/rest/entity/verification.entity.ts",
          "hash": "2009828148406600256"
        },
        {
          "file": "apps/api/src/models/verifications/rest/verifications.controller.ts",
          "hash": "9633022585944784903"
        },
        {
          "file": "apps/api/src/models/verifications/verifications.module.ts",
          "hash": "14592269712637543058"
        },
        {
          "file": "apps/api/src/schema.gql",
          "hash": "10876517553859208028"
        },
        {
          "file": "apps/api/test/app.e2e-spec.ts",
          "hash": "15142680097789702029"
        },
        {
          "file": "apps/api/test/jest-e2e.json",
          "hash": "7570273541430074424"
        },
        {
          "file": "apps/api/tsconfig.build.json",
          "hash": "276845246908739715"
        },
        {
          "file": "apps/api/tsconfig.json",
          "hash": "1876265833229380624"
        }
      ],
      "@autospace/ui": [
        {
          "file": "libs/ui/.eslintrc.json",
          "hash": "2410745308925489546"
        },
        {
          "file": "libs/ui/.gitignore",
          "hash": "14795959431407842278"
        },
        {
          "file": "libs/ui/README.md",
          "hash": "10011398316402962549"
        },
        {
          "file": "libs/ui/next.config.mjs",
          "hash": "3099306030354460128"
        },
        {
          "file": "libs/ui/package-lock.json",
          "hash": "13491096397384813811"
        },
        {
          "file": "libs/ui/package.json",
          "hash": "15656823787358998826",
          "deps": [
            "npm:@types/node",
            "npm:@types/react",
            "npm:@types/react-dom",
            "npm:eslint",
            "npm:eslint-config-next@14.2.8",
            "npm:postcss",
            "npm:tailwindcss",
            "npm:typescript",
            "@autospace/forms",
            "@autospace/util",
            "npm:@headlessui/react",
            "npm:next@14.2.8",
            "npm:react",
            "npm:react-dom",
            "npm:react-map-gl",
            "npm:@emotion/react",
            "npm:@emotion/styled",
            "npm:@mui/material",
            "npm:mapbox-gl"
          ]
        },
        {
          "file": "libs/ui/postcss.config.mjs",
          "hash": "17882505348629598648"
        },
        {
          "file": "libs/ui/src/app/favicon.ico",
          "hash": "9157999678830540297"
        },
        {
          "file": "libs/ui/src/app/fonts/GeistMonoVF.woff",
          "hash": "17799230542345324615"
        },
        {
          "file": "libs/ui/src/app/fonts/GeistVF.woff",
          "hash": "6578897518916770501"
        },
        {
          "file": "libs/ui/src/app/globals.css",
          "hash": "13453412729399060383"
        },
        {
          "file": "libs/ui/src/app/layout.tsx",
          "hash": "14815181338251710490"
        },
        {
          "file": "libs/ui/src/app/page.tsx",
          "hash": "334034143564997744"
        },
        {
          "file": "libs/ui/src/components/atoms/Autocomplete.tsx",
          "hash": "2631273026340901042"
        },
        {
          "file": "libs/ui/src/components/atoms/Brand.tsx",
          "hash": "13530865859398274602"
        },
        {
          "file": "libs/ui/src/components/atoms/BrandIcon.tsx",
          "hash": "13039478846877273598"
        },
        {
          "file": "libs/ui/src/components/atoms/Button.tsx",
          "hash": "5064224201582019179"
        },
        {
          "file": "libs/ui/src/components/atoms/Container.tsx",
          "hash": "11773865927790994091"
        },
        {
          "file": "libs/ui/src/components/atoms/Dialog.tsx",
          "hash": "6134409037724057277"
        },
        {
          "file": "libs/ui/src/components/atoms/Form.tsx",
          "hash": "10119814195183772647"
        },
        {
          "file": "libs/ui/src/components/atoms/FormError.tsx",
          "hash": "9734022425772391576"
        },
        {
          "file": "libs/ui/src/components/atoms/HtmlInput.tsx",
          "hash": "4269163392476547267"
        },
        {
          "file": "libs/ui/src/components/atoms/HtmlLabel.tsx",
          "hash": "15611936887369854455"
        },
        {
          "file": "libs/ui/src/components/atoms/ParkingIcon.tsx",
          "hash": "5034911977287356336"
        },
        {
          "file": "libs/ui/src/components/molecules/AuthLayout.tsx",
          "hash": "4328824551671493663"
        },
        {
          "file": "libs/ui/src/components/molecules/IconTypes.tsx",
          "hash": "2980512032107186315"
        },
        {
          "file": "libs/ui/src/components/molecules/LogoutButton.tsx",
          "hash": "10443980874709706752"
        },
        {
          "file": "libs/ui/src/components/molecules/SessionProvider.tsx",
          "hash": "8801271450817633589"
        },
        {
          "file": "libs/ui/src/components/molecules/UserInfo.tsx",
          "hash": "7665772310431570082"
        },
        {
          "file": "libs/ui/src/components/organisms/Header.tsx",
          "hash": "3194349568258914015"
        },
        {
          "file": "libs/ui/src/components/organisms/Sidebar.tsx",
          "hash": "10107497906072445818"
        },
        {
          "file": "libs/ui/src/components/organisms/map/CurrentLocationButton.tsx",
          "hash": "8923651528552190697"
        },
        {
          "file": "libs/ui/src/components/organisms/map/Map.tsx",
          "hash": "10678281436049781079"
        },
        {
          "file": "libs/ui/src/components/organisms/map/MapMarker.tsx",
          "hash": "10577167791065958650"
        },
        {
          "file": "libs/ui/src/components/organisms/map/Panel.tsx",
          "hash": "17547295360249551735"
        },
        {
          "file": "libs/ui/src/components/organisms/map/SearchPlacesBox.tsx",
          "hash": "14828217191486140584"
        },
        {
          "file": "libs/ui/src/components/organisms/map/ZoomControls.tsx",
          "hash": "14292658393930022187"
        },
        {
          "file": "libs/ui/src/components/organisms/map/map.css",
          "hash": "6873615366755814396"
        },
        {
          "file": "libs/ui/src/components/organisms/search/GarageMarker.tsx",
          "hash": "7889429319940488105"
        },
        {
          "file": "libs/ui/src/components/organisms/search/ShowGarages.tsx",
          "hash": "7371997333883078124"
        },
        {
          "file": "libs/ui/src/components/templates/LoginForm.tsx",
          "hash": "13896704420083736137"
        },
        {
          "file": "libs/ui/src/components/templates/RegisterForm.tsx",
          "hash": "11536812887688962766"
        },
        {
          "file": "libs/ui/src/components/templates/SearchPage.tsx",
          "hash": "132657536998174561"
        },
        {
          "file": "libs/ui/src/styles/config.js",
          "hash": "8324048331580989744"
        },
        {
          "file": "libs/ui/tailwind.config.ts",
          "hash": "2544258114199104624"
        },
        {
          "file": "libs/ui/tsconfig.json",
          "hash": "12090993031857468561"
        },
        {
          "file": "libs/ui/types.d.ts",
          "hash": "2811942231022728679"
        },
        {
          "file": "libs/ui/src/components/atoms/Dot.tsx",
          "hash": "1522095667562031444"
        },
        {
          "file": "libs/ui/src/components/molecules/FilterHeading.tsx",
          "hash": "15576914556531170853"
        },
        {
          "file": "libs/ui/src/components/molecules/RangeSlider.tsx",
          "hash": "12810719382320512578"
        },
        {
          "file": "libs/ui/src/components/molecules/ToggleButtonGroup.tsx",
          "hash": "2702096167080810763"
        },
        {
          "file": "libs/ui/src/components/organisms/search/FilterSidebar.tsx",
          "hash": "7254396695344052729"
        },
        {
          "file": "libs/ui/src/components/organisms/NavSidebar.tsx",
          "hash": "15155577328879109017"
        }
      ],
      "@autospace/sample-lib": [
        {
          "file": "libs/sample-lib/index.ts",
          "hash": "3876930869660554065"
        },
        {
          "file": "libs/sample-lib/package-lock.json",
          "hash": "2054902579136608719"
        },
        {
          "file": "libs/sample-lib/package.json",
          "hash": "6993432985236782914"
        },
        {
          "file": "libs/sample-lib/tsconfig.json",
          "hash": "14590710882709848906"
        }
      ],
      "@autospace/web": [
        {
          "file": "apps/web/.env.example",
          "hash": "631964354844325728"
        },
        {
          "file": "apps/web/.eslintrc.json",
          "hash": "10616060546436571437"
        },
        {
          "file": "apps/web/.gitignore",
          "hash": "14795959431407842278"
        },
        {
          "file": "apps/web/README.md",
          "hash": "17700555159788556570"
        },
        {
          "file": "apps/web/next.config.mjs",
          "hash": "3099306030354460128"
        },
        {
          "file": "apps/web/package.json",
          "hash": "17153964682461908489",
          "deps": [
            "npm:@types/node",
            "npm:@types/react",
            "npm:@types/react-dom",
            "npm:autoprefixer",
            "npm:eslint",
            "npm:eslint-config-next",
            "npm:postcss",
            "npm:tailwindcss",
            "npm:typescript",
            "@autospace/network",
            "@autospace/sample-lib",
            "@autospace/ui",
            "npm:@tabler/icons-react",
            "npm:next",
            "npm:next-auth",
            "npm:react",
            "npm:react-dom"
          ]
        },
        {
          "file": "apps/web/postcss.config.js",
          "hash": "1579725330904862112"
        },
        {
          "file": "apps/web/public/next.svg",
          "hash": "8300767200008744458"
        },
        {
          "file": "apps/web/public/user.png",
          "hash": "16941821795138000203"
        },
        {
          "file": "apps/web/public/vercel.svg",
          "hash": "2376673330454856631"
        },
        {
          "file": "apps/web/src/app/about/page.tsx",
          "hash": "16589847121499675601"
        },
        {
          "file": "apps/web/src/app/api/auth/[...nextauth]/route.ts",
          "hash": "6856419169857469093"
        },
        {
          "file": "apps/web/src/app/api/auth/token/route.ts",
          "hash": "17984012397210975190"
        },
        {
          "file": "apps/web/src/app/favicon.ico",
          "hash": "9157999678830540297"
        },
        {
          "file": "apps/web/src/app/layout.tsx",
          "hash": "11126362439246274654"
        },
        {
          "file": "apps/web/src/app/login/page.tsx",
          "hash": "14866151659755759388"
        },
        {
          "file": "apps/web/src/app/page.tsx",
          "hash": "10817460152580837333"
        },
        {
          "file": "apps/web/src/app/register/page.tsx",
          "hash": "17488438096447947484"
        },
        {
          "file": "apps/web/src/app/search/page.tsx",
          "hash": "6031963771089208747"
        },
        {
          "file": "apps/web/tailwind.config.ts",
          "hash": "16967495277415250122"
        },
        {
          "file": "apps/web/tsconfig.json",
          "hash": "4320684160905164141"
        },
        {
          "file": "apps/web/types.d.ts",
          "hash": "2811942231022728679"
        }
      ],
      "@autospace/util": [
        {
          "file": "libs/util/constants.ts",
          "hash": "474942991662045432"
        },
        {
          "file": "libs/util/date.ts",
          "hash": "6757909678281977280"
        },
        {
          "file": "libs/util/hooks/async.ts",
          "hash": "5625595127229105220"
        },
        {
          "file": "libs/util/hooks/dialog.ts",
          "hash": "1238686928551521995"
        },
        {
          "file": "libs/util/hooks/keys.ts",
          "hash": "15976907566512513771"
        },
        {
          "file": "libs/util/hooks/location.ts",
          "hash": "17029679564999789924"
        },
        {
          "file": "libs/util/package-lock.json",
          "hash": "2219374397245951225"
        },
        {
          "file": "libs/util/package.json",
          "hash": "18258404626517800846"
        },
        {
          "file": "libs/util/types.ts",
          "hash": "6997272884153512889"
        }
      ]
    }
  }
}